geospatial_analysis/__init__.py
geospatial_analysis/common.py
geospatial_analysis/geospatial_analysis.py
geospatial_analysis-0.0.1.dist-info/LICENSE
geospatial_analysis-0.0.1.dist-info/METADATA
geospatial_analysis-0.0.1.dist-info/WHEEL
geospatial_analysis-0.0.1.dist-info/entry_points.txt
geospatial_analysis-0.0.1.dist-info/top_level.txt
geospatial_analysis-0.0.1.dist-info/RECORD
